scrapy_ai/__init__.py
scrapy_ai/base_spider.py
scrapy_ai/list_spider.py
scrapy_ai-0.0.1.dist-info/LICENSE
scrapy_ai-0.0.1.dist-info/METADATA
scrapy_ai-0.0.1.dist-info/WHEEL
scrapy_ai-0.0.1.dist-info/top_level.txt
scrapy_ai-0.0.1.dist-info/RECORD
