Metadata-Version: 2.1
Name: scrapy-ai
Version: 0.0.1
Summary: AI-powered scrapy plugin
Home-page: https://github.com/crawlab-team/scrapy-ai
Author: Marvin Zhang
Author-email: tikazyq@163.com
License: MIT
Keywords: scrapy,ai,plugin,crawlab
License-File: LICENSE
